sanic_session/__init__.py
sanic_session/aioredis.py
sanic_session/base.py
sanic_session/memcache.py
sanic_session/memory.py
sanic_session/mongodb.py
sanic_session/redis.py
sanic_session/utils.py
sanic_session-0.8.0.dist-info/LICENSE
sanic_session-0.8.0.dist-info/METADATA
sanic_session-0.8.0.dist-info/WHEEL
sanic_session-0.8.0.dist-info/top_level.txt
sanic_session-0.8.0.dist-info/RECORD
