Metadata-Version: 2.1
Name: sanic_session
Version: 0.8.0
Summary: Provides server-backed sessions for Sanic using Redis, Memcache and more.
Home-page: http://github.com/subyraman/sanic_session
Author: Suby Raman, Mikhail Kashkin
Author-email: m@xen.ru
License: MIT
Keywords: sessions,sanic,redis,memcache
Platform: UNKNOWN
Classifier: Framework :: AsyncIO
Classifier: Development Status :: 5 - Production/Stable
Classifier: License :: OSI Approved :: MIT License
Classifier: Programming Language :: Python :: 3.6
Classifier: Programming Language :: Python :: 3.7
Classifier: Programming Language :: Python :: 3.8
Classifier: Programming Language :: Python :: 3.9
Classifier: Programming Language :: Python :: 3 :: Only
Classifier: Programming Language :: Python :: Implementation :: CPython
Classifier: Programming Language :: Python :: Implementation :: PyPy
Classifier: Topic :: Internet :: WWW/HTTP :: Session
Provides-Extra: aioredis
Provides-Extra: redis
Provides-Extra: mongo
Provides-Extra: aiomcache
Provides-Extra: dev
